vllm/_C.abi3.so
vllm/__init__.py
vllm/_custom_ops.py
vllm/_ipex_ops.py
vllm/_moe_C.abi3.so
vllm/_punica_C.abi3.so
vllm/block.py
vllm/config.py
vllm/envs.py
vllm/inputs.py
vllm/logger.py
vllm/outputs.py
vllm/pooling_params.py
vllm/py.typed
vllm/sampling_params.py
vllm/sequence.py
vllm/tracing.py
vllm/utils.py
vllm/version.py
vllm/attention/__init__.py
vllm/attention/layer.py
vllm/attention/selector.py
vllm/attention/backends/__init__.py
vllm/attention/backends/abstract.py
vllm/attention/backends/blocksparse_attn.py
vllm/attention/backends/flash_attn.py
vllm/attention/backends/flashinfer.py
vllm/attention/backends/ipex_attn.py
vllm/attention/backends/pallas.py
vllm/attention/backends/rocm_flash_attn.py
vllm/attention/backends/torch_sdpa.py
vllm/attention/backends/xformers.py
vllm/attention/ops/__init__.py
vllm/attention/ops/ipex_attn.py
vllm/attention/ops/paged_attn.py
vllm/attention/ops/prefix_prefill.py
vllm/attention/ops/triton_flash_attention.py
vllm/attention/ops/blocksparse_attention/__init__.py
vllm/attention/ops/blocksparse_attention/blocksparse_attention_kernel.py
vllm/attention/ops/blocksparse_attention/interface.py
vllm/attention/ops/blocksparse_attention/utils.py
vllm/core/__init__.py
vllm/core/block_manager_v1.py
vllm/core/block_manager_v2.py
vllm/core/embedding_model_block_manager.py
vllm/core/evictor_v1.py
vllm/core/evictor_v2.py
vllm/core/interfaces.py
vllm/core/policy.py
vllm/core/scheduler.py
vllm/core/block/__init__.py
vllm/core/block/block_table.py
vllm/core/block/common.py
vllm/core/block/cpu_gpu_block_allocator.py
vllm/core/block/interfaces.py
vllm/core/block/naive_block.py
vllm/core/block/prefix_caching_block.py
vllm/core/block/utils.py
vllm/distributed/__init__.py
vllm/distributed/communication_op.py
vllm/distributed/parallel_state.py
vllm/distributed/utils.py
vllm/distributed/device_communicators/__init__.py
vllm/distributed/device_communicators/cuda_wrapper.py
vllm/distributed/device_communicators/custom_all_reduce.py
etched_blitz-0.0.1.dev1.dist-info/LICENSE
etched_blitz-0.0.1.dev1.dist-info/METADATA
etched_blitz-0.0.1.dev1.dist-info/WHEEL
etched_blitz-0.0.1.dev1.dist-info/top_level.txt
etched_blitz-0.0.1.dev1.dist-info/RECORD
