Metadata-Version: 2.1
Name: etched-blitz
Version: 0.0.1.dev1
Summary: A high-throughput and memory-efficient inference and serving engine for LLMs
Home-page: https://github.com/etched-ai/blitz
Author: Etched Team
License: Apache 2.0
Project-URL: Homepage, https://github.com/etched-ai/blitz
Project-URL: Documentation, https://etched-ai.github.io/blitz/
Classifier: Programming Language :: Python :: 3.8
Classifier: Programming Language :: Python :: 3.9
Classifier: Programming Language :: Python :: 3.10
Classifier: Programming Language :: Python :: 3.11
Classifier: License :: OSI Approved :: Apache Software License
Classifier: Topic :: Scientific/Engineering :: Artificial Intelligence
Requires-Python: >=3.8
License-File: LICENSE
Requires-Dist: cmake >=3.21
Requires-Dist: ninja
Requires-Dist: psutil
Requires-Dist: sentencepiece
Requires-Dist: numpy <2.0.0
Requires-Dist: requests
Requires-Dist: tqdm
Requires-Dist: py-cpuinfo
Requires-Dist: transformers >=4.40.0
Requires-Dist: tokenizers >=0.19.1
Requires-Dist: fastapi
Requires-Dist: aiohttp
Requires-Dist: openai
Requires-Dist: uvicorn[standard]
Requires-Dist: pydantic >=2.0
Requires-Dist: pillow
Requires-Dist: prometheus-client >=0.18.0
Requires-Dist: prometheus-fastapi-instrumentator >=7.0.0
Requires-Dist: tiktoken >=0.6.0
Requires-Dist: lm-format-enforcer ==0.10.1
Requires-Dist: outlines >=0.0.43
Requires-Dist: typing-extensions
Requires-Dist: filelock >=3.10.4
Requires-Dist: triton >=2.2.0
Requires-Dist: torch ==2.3.1+cpu ; platform_machine != "ppc64le"
Requires-Dist: torchvision ==0.18.1+cpu ; platform_machine != "ppc64le"
Provides-Extra: tensorizer
Requires-Dist: tensorizer >=2.9.0 ; extra == 'tensorizer'
